{
  "operator": {
    "blaze": {
      "name": "blaze",
      "prof": "GUARD",
      "posType": "MELEE",
      "rarity": 6,
      "maxHp": 2821,
      "atk": 765,
      "def": 370,
      "resist": 0,
      "cost": 24,
      "block": 3,
      "atkTime": 1.2,
      "rspTime": 70.0,
      "hpRecoveryPerSec": 0,
      "spRecoveryPerSec": 1.0,
      "tauntLevel": 0,
      "stunImmune": false,
      "silenceImmune": false,
      "atkArea": [
        [0, 0],
        [1, 0]
      ]
    },
    "cardigan": {
      "name": "cardigan",
      "prof": "DEFENDER",
      "posType": "MELEE",
      "rarity": 3,
      "maxHp": 2130,
      "atk": 305,
      "def": 475,
      "resist": 0,
      "cost": 18,
      "block": 3,
      "atkTime": 1.2,
      "rspTime": 70.0,
      "hpRecoveryPerSec": 0,
      "spRecoveryPerSec": 1.0,
      "tauntLevel": 0,
      "stunImmune": false,
      "silenceImmune": false,
      "atkArea": [
        [0, 0],
        [1, 0]
      ]
    },
    "ceylon": {
      "name": "ceylon",
      "prof": "MEDIC",
      "posType": "RANGED",
      "rarity": 5,
      "maxHp": 1455,
      "atk": 442,
      "def": 126,
      "resist": 5,
      "cost": 22,
      "block": 1,
      "atkTime": 2.85,
      "rspTime": 80.0,
      "hpRecoveryPerSec": 0,
      "spRecoveryPerSec": 1.0,
      "tauntLevel": 0,
      "stunImmune": false,
      "silenceImmune": false,
      "atkArea": [
        [0, 0],
        [0, 1],
        [0, 2],
        [0, -1],
        [0, -2],
        [1, 0],
        [1, 1],
        [1, 2],
        [1, -1],
        [1, -2],
        [2, 0],
        [2, 1],
        [2, 2],
        [2, -1],
        [2, -2],
        [3, 0],
        [3, 1],
        [3, -1]
      ]
    },
    "durin": {
      "name": "durin",
      "prof": "CASTER",
      "posType": "RANGED",
      "rarity": 2,
      "maxHp": 952,
      "atk": 340,
      "def": 62,
      "resist": 10,
      "cost": 12,
      "block": 1,
      "atkTime": 1.6,
      "rspTime": 70.0,
      "hpRecoveryPerSec": 0,
      "spRecoveryPerSec": 1.0,
      "tauntLevel": 0,
      "stunImmune": false,
      "silenceImmune": false,
      "atkArea": [
        [0, 0],
        [0, 1],
        [0, -1],
        [1, 0],
        [1, 1],
        [1, -1],
        [2, 0],
        [2, 1],
        [2, -1]
      ]
    },
    "haze": {
      "name": "haze",
      "prof": "CASTER",
      "posType": "RANGED",
      "rarity": 4,
      "maxHp": 1420,
      "atk": 583,
      "def": 110,
      "resist": 20,
      "cost": 19,
      "block": 1,
      "atkTime": 1.6,
      "rspTime": 70.0,
      "hpRecoveryPerSec": 0,
      "spRecoveryPerSec": 1.0,
      "tauntLevel": 0,
      "stunImmune": false,
      "silenceImmune": false,
      "atkArea": [
        [0, 1],
        [0, 0],
        [0, -1],
        [1, 1],
        [1, 0],
        [1, -1],
        [2, 1],
        [2, 0],
        [2, -1],
        [3, 0]
      ]
    },
    "kroos": {
      "name": "kroos",
      "prof": "SNIPER",
      "posType": "RANGED",
      "rarity": 3,
      "maxHp": 1060,
      "atk": 375,
      "def": 126,
      "resist": 0,
      "cost": 11,
      "block": 1,
      "atkTime": 1.0,
      "rspTime": 70.0,
      "hpRecoveryPerSec": 0,
      "spRecoveryPerSec": 1.0,
      "tauntLevel": 0,
      "stunImmune": false,
      "silenceImmune": false,
      "atkArea": [
        [0, 1],
        [0, 0],
        [0, -1],
        [1, 1],
        [1, 0],
        [1, -1],
        [2, 1],
        [2, 0],
        [2, -1],
        [3, 1],
        [3, 0],
        [3, -1]
      ]
    },
    "lancet2": {
      "name": "lancet2",
      "prof": "MEDIC",
      "posType": "RANGED",
      "rarity": 1,
      "maxHp": 435,
      "atk": 70,
      "def": 27,
      "resist": 0,
      "cost": 3,
      "block": 1,
      "atkTime": 2.85,
      "rspTime": 200.0,
      "hpRecoveryPerSec": 0,
      "spRecoveryPerSec": 1.0,
      "tauntLevel": 0,
      "stunImmune": false,
      "silenceImmune": false,
      "atkArea": [
        [0, 1],
        [0, 0],
        [0, -1],
        [1, 1],
        [1, 0],
        [1, -1],
        [2, 1],
        [2, 0],
        [2, -1],
        [3, 0]
      ]
    },
    "reed": {
      "name": "reed",
      "prof": "VANGUARD",
      "posType": "MELEE",
      "rarity": 5,
      "maxHp": 2215,
      "atk": 562,
      "def": 364,
      "resist": 0,
      "cost": 12,
      "block": 1,
      "atkTime": 1.0,
      "rspTime": 70.0,
      "hpRecoveryPerSec": 0,
      "spRecoveryPerSec": 1.0,
      "tauntLevel": 0,
      "stunImmune": false,
      "silenceImmune": false,
      "atkArea": [
        [0, 0],
        [1, 0]
      ]
    },
    "rope": {
      "name": "rope",
      "prof": "SPECIALIST",
      "posType": "MELEE",
      "rarity": 4,
      "maxHp": 1720,
      "atk": 728,
      "def": 325,
      "resist": 0,
      "cost": 12,
      "block": 2,
      "atkTime": 1.8,
      "rspTime": 70.0,
      "hpRecoveryPerSec": 0,
      "spRecoveryPerSec": 1.0,
      "tauntLevel": 0,
      "stunImmune": false,
      "silenceImmune": false,
      "atkArea": [
        [0, 0],
        [1, 0],
        [2, 0],
        [3, 0]
      ]
    },
    "silverash": {
      "name": "silverash",
      "prof": "GUARD",
      "posType": "MELEE",
      "rarity": 6,
      "maxHp": 2560,
      "atk": 713,
      "def": 397,
      "resist": 10,
      "cost": 20,
      "block": 2,
      "atkTime": 1.3,
      "rspTime": 70.0,
      "hpRecoveryPerSec": 0,
      "spRecoveryPerSec": 1.0,
      "tauntLevel": 0,
      "stunImmune": false,
      "silenceImmune": false,
      "atkArea": [
        [0, 1],
        [0, 0],
        [0, -1],
        [1, 1],
        [1, 0],
        [1, -1],
        [2, 0],
        [3, 0]
      ]
    },
    "sora": {
      "name": "sora",
      "prof": "SUPPORTER",
      "posType": "RANGED",
      "rarity": 5,
      "maxHp": 1356,
      "atk": 335,
      "def": 238,
      "resist": 0,
      "cost": 7,
      "block": 1,
      "atkTime": 1.0,
      "rspTime": 70.0,
      "hpRecoveryPerSec": 0,
      "spRecoveryPerSec": 1.0,
      "tauntLevel": 0,
      "stunImmune": false,
      "silenceImmune": false,
      "atkArea": [
        [-2, 0],
        [-1, 0],
        [-1, 1],
        [-1, -1],
        [0, 0],
        [0, 1],
        [0, 2],
        [0, -1],
        [0, -2],
        [1, 0],
        [1, 1],
        [1, -1],
        [2, 0]
      ]
    },
    "vermeil": {
      "name": "vermeil",
      "prof": "SNIPER",
      "posType": "RANGED",
      "rarity": 4,
      "maxHp": 1230,
      "atk": 485,
      "def": 162,
      "resist": 0,
      "cost": 12,
      "block": 1,
      "atkTime": 1.0,
      "rspTime": 70.0,
      "hpRecoveryPerSec": 0,
      "spRecoveryPerSec": 1.0,
      "tauntLevel": 0,
      "stunImmune": false,
      "silenceImmune": false,
      "atkArea": [
        [0, 0],
        [0, 1],
        [0, -1],
        [1, 0],
        [1, 1],
        [1, -1],
        [2, 0],
        [2, 1],
        [2, -1],
        [3, 0],
        [3, 1],
        [3, -1]
      ]
    }
  },
  "enemy": {
    "slime": {
      "name": "slime",
      "maxHp": 550,
      "atk": 130,
      "def": 0,
      "resist": 0,
      "atkTime": 1.7,
      "hpRecoveryPerSec": 0,
      "moveSpd": 1.0,
      "massLv": 0,
      "stunImmune": false,
      "silenceImmune": false,
      "rangeRad": 0,
      "sizeAlpha": 0.8
    },
    "saber": {
      "name": "saber",
      "maxHp": 1650,
      "atk": 200,
      "def": 100,
      "resist": 0,
      "atkTime": 2.0,
      "hpRecoveryPerSec": 0,
      "moveSpd": 1.1,
      "massLv": 1,
      "stunImmune": false,
      "silenceImmune": false,
      "rangeRad": 0,
      "sizeAlpha": 0.8
    }
  }
}
